mit_moira.py
mit_moira-0.0.4.dist-info/METADATA
mit_moira-0.0.4.dist-info/RECORD
mit_moira-0.0.4.dist-info/WHEEL
mit_moira-0.0.4.dist-info/top_level.txt
