Metadata-Version: 2.1
Name: mit-moira
Version: 0.0.4
Summary: Python client for accessing MIT's Moira system
Home-page: https://github.com/mitodl/mit-moira
Author: MIT Office of Digital Learning
Author-email: odl@mit.edu
License: BSD
Platform: UNKNOWN
Classifier: License :: OSI Approved :: BSD License
Classifier: Programming Language :: Python :: 3
Classifier: Topic :: Internet
Requires-Dist: zeep
